anki_sqlalchemy/__init__.py
anki_sqlalchemy/py.typed
anki_sqlalchemy/sqlalchemy_fields.py
anki_sqlalchemy/sqlalchemy_models.py
anki_sqlalchemy/unicase.py
anki_sqlalchemy-0.3.0.dist-info/LICENSE
anki_sqlalchemy-0.3.0.dist-info/METADATA
anki_sqlalchemy-0.3.0.dist-info/WHEEL
anki_sqlalchemy-0.3.0.dist-info/entry_points.txt
anki_sqlalchemy-0.3.0.dist-info/top_level.txt
anki_sqlalchemy-0.3.0.dist-info/RECORD
