Metadata-Version: 2.1
Name: anki-sqlalchemy
Version: 0.3.0
Summary: Clean python interface for interacting with Anki's database
Home-page: https://github.com/AlexRiina/anki-sqlalchemy
Author: Alex Riina
Author-email: alex.riina@gmail.com
License: UNKNOWN
Platform: UNKNOWN
Classifier: Programming Language :: Python :: 3
Classifier: License :: OSI Approved :: MIT License
Classifier: Operating System :: OS Independent
Requires-Python: >=3.6
Requires-Dist: sqlalchemy
